{"stats":{"minecraft:killed":{"quack:duck":5},"minecraft:used":{"quack:cooked_duck":1,"minecraft:bow":8,"quack:duck_meat":1},"minecraft:picked_up":{"quack:duck_meat":5,"quack:duck_egg":4,"quack:duck_feather":4},"minecraft:custom":{"minecraft:sprint_one_cm":767,"minecraft:time_since_rest":8797,"minecraft:walk_one_cm":14919,"minecraft:total_world_time":11713,"minecraft:leave_game":1,"minecraft:fly_one_cm":399915,"minecraft:mob_kills":5,"minecraft:walk_on_water_one_cm":2125,"minecraft:sneak_time":66,"minecraft:play_time":8797,"minecraft:jump":61,"minecraft:time_since_death":8797}},"DataVersion":4440}